tdtui/__init__.py
tdtui/main.py
tdtui/save_state.py
tdtui/widgets/color.py
tdtui/widgets/keybinds_helper.py
tdtui/widgets/task_input.py
tdtui/widgets/input_widgets/add_task_field.py
tdtui/widgets/input_widgets/select_color.py
tdtui/widgets/input_widgets/task_name.py
tdtui/widgets/pop_ups/existing_task_error.py
tdtui/widgets/pop_ups/task_properties.py
tdtui/widgets/tasks_widgets/completed_tasks_list.py
tdtui/widgets/tasks_widgets/incompleted_tasks_list.py
tdtui/widgets/tasks_widgets/task.py
tdtui/widgets/tasks_widgets/tasks_list.py
tdtui-1.0.dist-info/METADATA
tdtui-1.0.dist-info/WHEEL
tdtui-1.0.dist-info/entry_points.txt
tdtui-1.0.dist-info/top_level.txt
tdtui-1.0.dist-info/RECORD
