Metadata-Version: 2.4
Name: tdtui
Version: 1.0
Summary: A simple TODO app with terminal UI
Author: Malek Khaled
Project-URL: Github, https://github.com/Malek-Khaled/todo-tui
Requires-Python: >=3.7
Requires-Dist: urwid
Requires-Dist: appdirs
